package/__init__.py
package/IoTEdgeMessagePublisher/__init__.py
package/IoTEdgeMessagePublisher/publisher.py
tests/__init__.py
tests/IoTEdgeMessagePublisher/__init__.py
tests/IoTEdgeMessagePublisher/test_publisher.py
SpuhlLibrary-1.0.0.dist-info/METADATA
SpuhlLibrary-1.0.0.dist-info/WHEEL
SpuhlLibrary-1.0.0.dist-info/top_level.txt
SpuhlLibrary-1.0.0.dist-info/RECORD
