Metadata-Version: 2.1
Name: SpuhlLibrary
Version: 1.0.0
Summary: Azure IoT Library from Spuhl GmbH
Home-page: https://github.com/sagerpascal/Spuhl_IoT_Solution
Author: Luca Staehli, Pascal Sager
Author-email: UNKNOWN
License: UNKNOWN
Platform: UNKNOWN
Requires-Dist: azure-iothub-device-client (~=1.4.3)
